{
  "db_name": "PostgreSQL",
  "query": "UPDATE emulators SET name = $1, consoles = $2, platform = $3, run_command = $4, binary_name = $5, save_path = $6, save_extensions = $7, config_files = $8, zipped = $9 WHERE id = $10",
  "describe": {
    "columns": [],
    "parameters": {
      "Left": [
        "Varchar",
        "TextArray",
        "Varchar",
        "Text",
        "Text",
        "Text",
        "TextArray",
        "TextArray",
        "Bool",
        "Int8"
      ]
    },
    "nullable": []
  },
  "hash": "4d361393e84b0722c2c22c085ba6d999062fb39db630cea6ba9d290230f9acaa"
}
